name_conflict_resolver/__init__.py
name_conflict_resolver/name_conflict_resolver.py
name_conflict_resolver-0.0.1.dist-info/METADATA
name_conflict_resolver-0.0.1.dist-info/WHEEL
name_conflict_resolver-0.0.1.dist-info/top_level.txt
name_conflict_resolver-0.0.1.dist-info/RECORD
