Metadata-Version: 2.4
Name: name_conflict_resolver
Version: 0.0.1
Summary: A library for deciding how to rename conflicting file paths.
Author-email: Andrew Tapia <andrew.tapia@uky.edu>
License-Expression: MIT
Project-URL: Homepage, https://github.com/actapia/name_conflict_resolver
Project-URL: Bug Tracker, https://github.com/actapia/name_conflict_resolver
Requires-Python: >=3.11
